nctoolkit/__init__.py
nctoolkit/add_etc.py
nctoolkit/anomaly.py
nctoolkit/api.py
nctoolkit/append.py
nctoolkit/assign.py
nctoolkit/cdo_command.py
nctoolkit/cellareas.py
nctoolkit/centres.py
nctoolkit/checks.py
nctoolkit/cleanup.py
nctoolkit/clear.py
nctoolkit/compare.py
nctoolkit/compare_data.py
nctoolkit/corr.py
nctoolkit/create_ensemble.py
nctoolkit/crop.py
nctoolkit/deprecated.py
nctoolkit/distgrid.py
nctoolkit/drop.py
nctoolkit/ensembles.py
nctoolkit/esoteric.py
nctoolkit/experimental.py
nctoolkit/fill.py
nctoolkit/flatten.py
nctoolkit/fldstat.py
nctoolkit/format.py
nctoolkit/generate_grid.py
nctoolkit/inttime.py
nctoolkit/invert.py
nctoolkit/masking.py
nctoolkit/matchpoint.py
nctoolkit/mergers.py
nctoolkit/meridonials.py
nctoolkit/mp_adders.py
nctoolkit/mp_matchers.py
nctoolkit/mp_matchups.py
nctoolkit/nco_command.py
nctoolkit/phenology.py
nctoolkit/plot.py
nctoolkit/reduce.py
nctoolkit/reduce_grid.py
nctoolkit/regrid.py
nctoolkit/remove.py
nctoolkit/rename.py
nctoolkit/resample.py
nctoolkit/rollstat.py
nctoolkit/run.py
nctoolkit/runners.py
nctoolkit/runthis.py
nctoolkit/session.py
nctoolkit/set.py
nctoolkit/setters.py
nctoolkit/shape.py
nctoolkit/shift.py
nctoolkit/show.py
nctoolkit/split.py
nctoolkit/static_plot.py
nctoolkit/strip_vars.py
nctoolkit/subset.py
nctoolkit/sumall.py
nctoolkit/temp_file.py
nctoolkit/temporal_stat.py
nctoolkit/temporals.py
nctoolkit/thresholds.py
nctoolkit/to_lonlat.py
nctoolkit/to_nc.py
nctoolkit/toxarray.py
nctoolkit/tozlev.py
nctoolkit/unify.py
nctoolkit/utils.py
nctoolkit/validator.py
nctoolkit/validator_funs.py
nctoolkit/verticals.py
nctoolkit/zip.py
nctoolkit/zonals.py
nctoolkit-1.2.6.dist-info/licenses/LICENSE
nctoolkit-1.2.6.dist-info/METADATA
nctoolkit-1.2.6.dist-info/WHEEL
nctoolkit-1.2.6.dist-info/top_level.txt
nctoolkit-1.2.6.dist-info/RECORD
