Metadata-Version: 2.4
Name: nctoolkit
Version: 1.2.6
Summary: A Python package for netCDF analysis and post-processing
Home-page: https://github.com/pmlmodelling/nctoolkit
Author: Robert Wilson
Author-email: rwi@pml.ac.uk
Maintainer: Robert Wilson
Project-URL: Bug Tracker, https://github.com/pmlmodelling/nctoolkit/issues
Project-URL: Documentation, https://nctoolkit.readthedocs.io/en/stable
Project-URL: Source Code, https://github.com/pmlmodelling/nctoolkit
Classifier: License :: OSI Approved :: GNU General Public License v3 (GPLv3)
Classifier: Operating System :: POSIX :: Linux
Classifier: Operating System :: MacOS
Classifier: Programming Language :: Python :: 3.8
Classifier: Programming Language :: Python :: 3.9
Classifier: Programming Language :: Python :: 3.10
Classifier: Programming Language :: Python :: 3.11
Classifier: Programming Language :: Python :: 3.12
Requires-Python: >=3.6.1
License-File: LICENSE
Requires-Dist: xarray
Requires-Dist: netCDF4
Requires-Dist: hvplot
Requires-Dist: panel
Requires-Dist: pandas
Requires-Dist: ncplot>=0.2.8
Requires-Dist: dill
Requires-Dist: python-dateutil
Requires-Dist: matplotlib
Requires-Dist: multiprocess
Provides-Extra: complete
Requires-Dist: geoviews; extra == "complete"
Requires-Dist: rioxarray; extra == "complete"
Requires-Dist: cfchecker; extra == "complete"
Requires-Dist: geocube; extra == "complete"
Requires-Dist: geopandas; extra == "complete"
Dynamic: author
Dynamic: author-email
Dynamic: classifier
Dynamic: description
Dynamic: description-content-type
Dynamic: home-page
Dynamic: license-file
Dynamic: maintainer
Dynamic: project-url
Dynamic: provides-extra
Dynamic: requires-dist
Dynamic: requires-python
Dynamic: summary
